Trie/__init__.py
Trie/graph.py
Trie/trie.py
Trie/trie_cli.py
Trie/try.py
Trie2/__init__.py
Trie2/graph.py
Trie2/trie.py
Trie2/trie_cli.py
WordzFun-1.1.dist-info/METADATA
WordzFun-1.1.dist-info/WHEEL
WordzFun-1.1.dist-info/entry_points.txt
WordzFun-1.1.dist-info/top_level.txt
WordzFun-1.1.dist-info/RECORD
