Metadata-Version: 2.1
Name: WordzFun
Version: 1.1
Summary: Trie for slingshot takehome.
Home-page: UNKNOWN
Author: Sabad Modi
Author-email: sabadmodi@gmail.com
License: MIT
Keywords: trie slingshot words dictionary wordzfun english
Platform: UNKNOWN
Classifier: Programming Language :: Python :: 3
Classifier: License :: OSI Approved :: MIT License
Classifier: Operating System :: OS Independent
Requires-Dist: pydot
Requires-Dist: firebase-admin
Requires-Dist: PyInquirer
Requires-Dist: PyDictionary
Requires-Dist: translate
Requires-Dist: pyfiglet
Requires-Dist: nltk
